create_flask_api_app/__init__.py
create_flask_api_app/__main__.py
create_flask_api_app/create.py
create_flask_api_app/api_template/__init__.py
create_flask_api_app/api_template/app.py
create_flask_api_app/api_template/common/__init__.py
create_flask_api_app/api_template/common/util.py
create_flask_api_app/api_template/resources/__init__.py
create_flask_api_app/api_template/resources/example.py
create_flask_api_app-0.0.5.dist-info/LICENSE
create_flask_api_app-0.0.5.dist-info/METADATA
create_flask_api_app-0.0.5.dist-info/WHEEL
create_flask_api_app-0.0.5.dist-info/entry_points.txt
create_flask_api_app-0.0.5.dist-info/top_level.txt
create_flask_api_app-0.0.5.dist-info/RECORD
