Metadata-Version: 2.1
Name: create-flask-api-app
Version: 0.0.5
Summary: Creates python flask API application template
Home-page: https://github.com/ElvisRodriguez/create-flask-api-app
Author: Elvis Rodriguez
Author-email: elvisrodriguez1992@gmail.com
License: MIT
Project-URL: Bug Tracker, https://github.com/ElvisRodriguez.create-flask-api-app/issues
Platform: UNKNOWN
Classifier: Development Status :: 2 - Pre-Alpha
Classifier: Intended Audience :: Developers
Classifier: License :: OSI Approved :: MIT License
Classifier: Natural Language :: English
Classifier: Operating System :: POSIX :: Linux
Classifier: Programming Language :: Python :: 3
Classifier: Programming Language :: Python :: Implementation :: CPython
Classifier: Topic :: Software Development :: Code Generators
Requires-Python: >=3
License-File: LICENSE
Requires-Dist: flask
Requires-Dist: flask-restful
Requires-Dist: SQLAlchemy
